{
  "employee": [
    {
      "id": 1,
      "first_name": "Gennifer",
      "last_name": "Chesnut",
      "gender": "Female"
    },
    {
      "id": 2,
      "first_name": "Kirk",
      "last_name": "Hathwood",
      "gender": "Male"
    },
    {
      "id": 3,
      "first_name": "Wini",
      "last_name": "Gabbitas",
      "gender": "Female"
    },
    {
      "id": 4,
      "first_name": "Rhonda",
      "last_name": "McGookin",
      "gender": "Female"
    },
    {
      "id": 5,
      "first_name": "Rochelle",
      "last_name": "Tassell",
      "gender": "Female"
    },
    {
      "id": 6,
      "first_name": "Amelina",
      "last_name": "Rucklidge",
      "gender": "Female"
    },
    {
      "id": 7,
      "first_name": "Perri",
      "last_name": "Erangey",
      "gender": "Female"
    },
    {
      "id": 8,
      "first_name": "Nance",
      "last_name": "Sayer",
      "gender": "Female"
    },
    {
      "id": 9,
      "first_name": "Rollie",
      "last_name": "Knighton",
      "gender": "Male"
    },
    {
      "id": 10,
      "first_name": "Neel",
      "last_name": "Harrowing",
      "gender": "Male"
    },
    {
      "id": 11,
      "first_name": "Margi",
      "last_name": "Grimsdith",
      "gender": "Female"
    },
    {
      "id": 12,
      "first_name": "Corina",
      "last_name": "Drescher",
      "gender": "Female"
    },
    {
      "id": 13,
      "first_name": "Irv",
      "last_name": "Forsdike",
      "gender": "Male"
    },
    {
      "id": 14,
      "first_name": "Mauricio",
      "last_name": "Freestone",
      "gender": "Male"
    },
    {
      "id": 15,
      "first_name": "Rey",
      "last_name": "McGarvie",
      "gender": "Female"
    },
    {
      "id": 16,
      "first_name": "Costanza",
      "last_name": "Moncreif",
      "gender": "Female"
    },
    {
      "id": 17,
      "first_name": "Kort",
      "last_name": "Burrows",
      "gender": "Male"
    },
    {
      "id": 18,
      "first_name": "Bea",
      "last_name": "Mickelwright",
      "gender": "Female"
    },
    {
      "id": 19,
      "first_name": "Albrecht",
      "last_name": "Verbrugghen",
      "gender": "Male"
    },
    {
      "id": 20,
      "first_name": "Carlos",
      "last_name": "Ireson",
      "gender": "Male"
    },
    {
      "id": 21,
      "first_name": "Jacquelynn",
      "last_name": "Splain",
      "gender": "Female"
    },
    {
      "id": 22,
      "first_name": "Mickie",
      "last_name": "Brotherhead",
      "gender": "Male"
    },
    {
      "id": 23,
      "first_name": "Patti",
      "last_name": "Lippo",
      "gender": "Female"
    },
    {
      "id": 24,
      "first_name": "Chloe",
      "last_name": "Gauntley",
      "gender": "Female"
    },
    {
      "id": 25,
      "first_name": "Philomena",
      "last_name": "Masey",
      "gender": "Female"
    },
    {
      "id": 26,
      "first_name": "Carolina",
      "last_name": "Sweetlove",
      "gender": "Female"
    },
    {
      "id": 27,
      "first_name": "Raleigh",
      "last_name": "Druhan",
      "gender": "Male"
    },
    {
      "id": 28,
      "first_name": "Rosene",
      "last_name": "Bradforth",
      "gender": "Female"
    },
    {
      "id": 29,
      "first_name": "Byrle",
      "last_name": "Eveque",
      "gender": "Male"
    },
    {
      "id": 30,
      "first_name": "Denna",
      "last_name": "Pachmann",
      "gender": "Female"
    }
  ]
}
